emnist/__init__.py
emnist-0.0.dist-info/LICENSE
emnist-0.0.dist-info/METADATA
emnist-0.0.dist-info/WHEEL
emnist-0.0.dist-info/top_level.txt
emnist-0.0.dist-info/RECORD
