Metadata-Version: 2.1
Name: emnist
Version: 0.0
Summary: Extended MNIST - Python Package
Home-page: https://github.com/hosford42/EMNIST
Author: Aaron Hosford
Author-email: hosford42@gmail.com
License: UNKNOWN
Project-URL: The EMNIST Dataset, https://www.nist.gov/itl/iad/image-group/emnist-dataset
Project-URL: The EMNIST Paper, https://arxiv.org/abs/1702.05373v1
Keywords: MNIST EMNIST image recognition data dataset numpy idx neural networkmachine learning
Platform: UNKNOWN
Classifier: Development Status :: 3 - Alpha
Classifier: Intended Audience :: Science/Research
Classifier: License :: OSI Approved :: MIT License
Classifier: Natural Language :: English
Classifier: Operating System :: OS Independent
Classifier: Programming Language :: Python :: 3
Classifier: Topic :: Scientific/Engineering :: Artificial Intelligence
Classifier: Topic :: Scientific/Engineering :: Image Recognition
Requires-Python: >=3.0
Requires-Dist: numpy
Requires-Dist: requests
Requires-Dist: tqdm
Provides-Extra: inspect
Requires-Dist: matplotlib ; extra == 'inspect'
